office/__init__.py
office/attribute.py
office/blob.py
office/config.py
office/fluent.py
office/office.py
office/query.py
office/token.py
office/calendar/__init__.py
office/calendar/calendar.py
office/calendar/event.py
office/calendar/service.py
office/outlook/__init__.py
office/outlook/folder.py
office/outlook/message.py
office/outlook/service.py
office/people/__init__.py
office/people/contact.py
office/people/folder.py
office/people/service.py
office/resources/__init__.py
office/resources/blob_content_types.py
office365-0.3.15.dist-info/LICENSE
office365-0.3.15.dist-info/METADATA
office365-0.3.15.dist-info/WHEEL
office365-0.3.15.dist-info/top_level.txt
office365-0.3.15.dist-info/RECORD
