Metadata-Version: 2.1
Name: office365
Version: 0.3.15
Summary: A wrapper around O365 offering subclasses with additional utility methods.
Home-page: https://github.com/matthewgdv/office
Author: Matt GdV
Author-email: matthewgdv@gmail.com
License: MIT
Platform: UNKNOWN
Classifier: Development Status :: 3 - Alpha
Classifier: Intended Audience :: Developers
Classifier: Programming Language :: Python :: 3.8
